Workbook

Sheet Customers
A1: CustomerID | B1: FirstName | C1: LastName | D1: Gender | E1: BirthDate | F1: City | G1: JoinDate
A2: C001 | B2: Michael | C2: Davis | D2: M | E2: 35319 | F2: Osborneport | G2: 44829
A3: C002 | B3: Michael | C3: Miller | D3: M | E3: 21780 | F3: New Gabrielleport | G3: 44138
A4: C003 | B4: Carol | C4: Hays | D4: F | E4: 38461 | F4: Port Allen | G4: 45334
A5: C004 | B5: Joseph | C5: Ward | D5: M | E5: 33771 | F5: East Edgarborough | G5: 45544
A6: C005 | B6: Jamie | C6: Salinas | D6: M | E6: 33773 | F6: Port Kimberly | G6: 44616
A7: C006 | B7: Danny | C7: Moore | D7: M | E7: 31688 | F7: Costaberg | G7: 44751
A8: C007 | B8: Erin | C8: Walker | D8: M | E8: 31058 | F8: West Jasmine | G8: 44482
A9: C008 | B9: Isaiah | C9: Williams | D9: M | E9: 22233 | F9: New Michaelland | G9: 45720
A10: C009 | B10: Richard | C10: Pacheco | D10: F | E10: 38214 | F10: West Lisaville | G10: 45764
A11: C010 | B11: Catherine | C11: Rice | D11: M | E11: 28106 | F11: West Carol | G11: 45861
A12: C011 | B12: Haley | C12: Williams | D12: M | E12: 35492 | F12: Leburgh | G12: 45058
A13: C012 | B13: Dale | C13: Perry | D13: M | E13: 32850 | F13: Lake Dawn | G13: 44393
... A201: C200 | B201: Ronald | C201: Haley | D201: M | E201: 37249 | F201: Jenniferbury | G201: 45832

Sheet Products
A1: ProductID | B1: ProductName | C1: Category | D1: SubCategory | E1: UnitPrice | F1: CostPrice
A2: P001 | B2: Like Camera | C2: Electronics | D2: Camera | E2: 1673.69 | F2: 1323.38
A3: P002 | B3: Audience Television | C3: Electronics | D3: Television | E3: 818.76 | F3: 527.62
A4: P003 | B4: Here Footwear | C4: Fashion | D4: Footwear | E4: 337.63 | F4: 169.03
A5: P004 | B5: Four Accessories | C5: Fashion | D5: Accessories | E5: 1853.77 | F5: 1363.52
A6: P005 | B6: Knowledge Bags | C6: Fashion | D6: Bags | E6: 1396.22 | F6: 1004.09
A7: P006 | B7: Company Fruits | C7: Groceries | D7: Fruits | E7: 318.05 | F7: 187.34
A8: P007 | B8: Understand Camera | C8: Electronics | D8: Camera | E8: 1474.12 | F8: 764.02
A9: P008 | B9: Recognize Footwear | C9: Fashion | D9: Footwear | E9: 109.78 | F9: 70.59
A10: P009 | B10: Us Snacks | C10: Groceries | D10: Snacks | E10: 123.19 | F10: 80.36
A11: P010 | B11: Step Smartphone | C11: Electronics | D11: Smartphone | E11: 1194.12 | F11: 838.95
A12: P011 | B12: Either Headphones | C12: Electronics | D12: Headphones | E12: 248.57 | F12: 190.67
A13: P012 | B13: Above Camera | C13: Electronics | D13: Camera | E13: 1193.09 | F13: 818.24
... A51: P050 | B51: Maybe Footwear | C51: Fashion | D51: Footwear | E51: 1044.64 | F51: 775.07

Sheet Stores
A1: StoreID | B1: StoreName | C1: City | D1: Region
A2: S001 | B2: MegaMart Jimenezborough | C2: Jimenezborough | D2: South
A3: S002 | B3: MegaMart Peckmouth | C3: Peckmouth | D3: East
A4: S003 | B4: MegaMart New Michele | C4: New Michele | D4: West
A5: S004 | B5: MegaMart Brianahaven | C5: Brianahaven | D5: North
A6: S005 | B6: MegaMart Johnmouth | C6: Johnmouth | D6: East

Sheet Transactions
A1: TransactionID | B1: Date | C1: CustomerID | D1: ProductID | E1: StoreID | F1: Quantity | G1: Discount | H1: PaymentMethod
A2: T00001 | B2: 45461 | C2: C160 | D2: P014 | E2: S003 | F2: 1 | G2: 0.1 | H2: Bank Transfer
A3: T00002 | B3: 45232 | C3: C171 | D3: P030 | E3: S004 | F3: 3 | G3: 0.15 | H3: Bank Transfer
A4: T00003 | B4: 45379 | C4: C142 | D4: P002 | E4: S002 | F4: 2 | G4: 0.15 | H4: Mobile Money
A5: T00004 | B5: 45458 | C5: C174 | D5: P050 | E5: S002 | F5: 5 | G5: 0.1 | H5: Mobile Money
A6: T00005 | B6: 45533 | C6: C141 | D6: P036 | E6: S001 | F6: 3 | G6: 0.1 | H6: Credit Card
A7: T00006 | B7: 45744 | C7: C111 | D7: P036 | E7: S005 | F7: 5 | G7: 0.1 | H7: Mobile Money
A8: T00007 | B8: 45605 | C8: C114 | D8: P009 | E8: S004 | F8: 2 | G8: 0.15 | H8: Credit Card
A9: T00008 | B9: 45440 | C9: C169 | D9: P005 | E9: S001 | F9: 3 | G9: 0.1 | H9: Cash
A10: T00009 | B10: 45539 | C10: C193 | D10: P035 | E10: S002 | F10: 3 | G10: 0.05 | H10: Credit Card
A11: T00010 | B11: 45459 | C11: C038 | D11: P045 | E11: S001 | F11: 1 | G11: 0.05 | H11: Mobile Money
A12: T00011 | B12: 45725 | C12: C157 | D12: P022 | E12: S001 | F12: 4 | G12: 0.15 | H12: Credit Card
A13: T00012 | B13: 45449 | C13: C184 | D13: P042 | E13: S004 | F13: 4 | G13: 0.15 | H13: Credit Card
... A5001: T05000 | B5001: 45489 | C5001: C053 | D5001: P034 | E5001: S004 | F5001: 5 | G5001: 0.15 | H5001: Cash

Sheet Payment Method
A3: Payment Method | B3: Sum of Revenue | C3: Sum of Net Profit | D3: Count of TransactionID
A4: Bank Transfer | B4: 3684068.7 | C4: 900150.88 | D4: 1159
A5: Cash | B5: 3970392.4 | C5: 982164.83 | D5: 1284
A6: Credit Card | B6: 3974092.3 | C6: 984053.74 | D6: 1281
A7: Mobile Money | B7: 3846618.3 | C7: 959945.22 | D7: 1276
A8: Grand Total | B8: 15475172 | C8: 3826314.7 | D8: 5000

Sheet Sales_Master
A1: TransactionID | B1: Date | C1: CustomerID | D1: ProductID | E1: StoreID | F1: Quantity | G1: Discount | H1: PaymentMethod | I1: Unit Price | J1: Cost Price | K1: Category | L1: Sub Category | M1: Revenue | N1: Cost | O1: Profit | P1: Profit Margin | Q1: Discount Amount | R1: Net Revenue | S1: Net Profit | T1: Gender | U1: Birth date | V1: city | W1: joining date | X1: Age | Y1: Age Group
A2: T00001 | B2: 45461 | C2: C160 | D2: P014 | E2: S003 | F2: 1 | G2: 0.1 | H2: Bank Transfer | I2: =_xlfn.XLOOKUP(D2,Products!A:A,Products!E:E) -> 1342.75 | J2: =_xlfn.XLOOKUP(D2,Products!A:A,Products!F:F) -> 797.94 | K2: =_xlfn.XLOOKUP(D2,Products!A:A,Products!C:C) -> Fashion | L2: =_xlfn.XLOOKUP(D2,Products!A:A,Products!D:D) -> Clothing | M2: =F2*I2 -> 1342.75 | N2: =F2*J2 -> 797.94 | O2: =M2-N2 -> 544.81 | P2: =O2/M2 -> 0.40574195 | Q2: =M2*G2 -> 134.275 | R2: =M2-Q2 -> 1208.475 | S2: =R2-N2 -> 410.535 | T2: =_xlfn.XLOOKUP(C2,Customers!A:A,Customers!D:D) -> M | U2: =_xlfn.XLOOKUP(C2,Customers!A:A,Customers!E:E) -> 33491 | V2: =_xlfn.XLOOKUP(C2,Customers!A:A,Customers!F:F) -> Port Jacob | W2: =_xlfn.XLOOKUP(C2,Customers!A:A,Customers!G:G) -> 44496 | X2: =DATEDIF(U2, TODAY(),"Y") -> 34 | Y2: =IF(X2<=25,"18-25",IF(X2<=35,"26-35", IF(X2<=50,"36-50","50+"))) -> 26-35
A3: T00002 | B3: 45232 | C3: C171 | D3: P030 | E3: S004 | F3: 3 | G3: 0.15 | H3: Bank Transfer | I3: =_xlfn.XLOOKUP(D3,Products!A:A,Products!E:E) -> 29.24 | J3: =_xlfn.XLOOKUP(D3,Products!A:A,Products!F:F) -> 15.28 | K3: =_xlfn.XLOOKUP(D3,Products!A:A,Products!C:C) -> Fashion | L3: =_xlfn.XLOOKUP(D3,Products!A:A,Products!D:D) -> Watches | M3: =F3*I3 -> 87.72 | N3: =F3*J3 -> 45.84 | O3: =M3-N3 -> 41.88 | P3: =O3/M3 -> 0.47742818 | Q3: =M3*G3 -> 13.158 | R3: =M3-Q3 -> 74.562 | S3: =R3-N3 -> 28.722 | T3: =_xlfn.XLOOKUP(C3,Customers!A:A,Customers!D:D) -> M | U3: =_xlfn.XLOOKUP(C3,Customers!A:A,Customers!E:E) -> 34043 | V3: =_xlfn.XLOOKUP(C3,Customers!A:A,Customers!F:F) -> Robertsborough | W3: =_xlfn.XLOOKUP(C3,Customers!A:A,Customers!G:G) -> 45866 | X3: =DATEDIF(U3, TODAY(),"Y") -> 33 | Y3: =IF(X3<=25,"18-25",IF(X3<=35,"26-35", IF(X3<=50,"36-50","50+"))) -> 26-35
A4: T00003 | B4: 45379 | C4: C142 | D4: P002 | E4: S002 | F4: 2 | G4: 0.15 | H4: Mobile Money | I4: =_xlfn.XLOOKUP(D4,Products!A:A,Products!E:E) -> 818.76 | J4: =_xlfn.XLOOKUP(D4,Products!A:A,Products!F:F) -> 527.62 | K4: =_xlfn.XLOOKUP(D4,Products!A:A,Products!C:C) -> Electronics | L4: =_xlfn.XLOOKUP(D4,Products!A:A,Products!D:D) -> Television | M4: =F4*I4 -> 1637.52 | N4: =F4*J4 -> 1055.24 | O4: =M4-N4 -> 582.28 | P4: =O4/M4 -> 0.3555865 | Q4: =M4*G4 -> 245.628 | R4: =M4-Q4 -> 1391.892 | S4: =R4-N4 -> 336.652 | T4: =_xlfn.XLOOKUP(C4,Customers!A:A,Customers!D:D) -> M | U4: =_xlfn.XLOOKUP(C4,Customers!A:A,Customers!E:E) -> 38558 | V4: =_xlfn.XLOOKUP(C4,Customers!A:A,Customers!F:F) -> Joelborough | W4: =_xlfn.XLOOKUP(C4,Customers!A:A,Customers!G:G) -> 44192 | X4: =DATEDIF(U4, TODAY(),"Y") -> 20 | Y4: =IF(X4<=25,"18-25",IF(X4<=35,"26-35", IF(X4<=50,"36-50","50+"))) -> 18-25
A5: T00004 | B5: 45458 | C5: C174 | D5: P050 | E5: S002 | F5: 5 | G5: 0.1 | H5: Mobile Money | I5: =_xlfn.XLOOKUP(D5,Products!A:A,Products!E:E) -> 1044.64 | J5: =_xlfn.XLOOKUP(D5,Products!A:A,Products!F:F) -> 775.07 | K5: =_xlfn.XLOOKUP(D5,Products!A:A,Products!C:C) -> Fashion | L5: =_xlfn.XLOOKUP(D5,Products!A:A,Products!D:D) -> Footwear | M5: =F5*I5 -> 5223.2 | N5: =F5*J5 -> 3875.35 | O5: =M5-N5 -> 1347.85 | P5: =O5/M5 -> 0.25805062 | Q5: =M5*G5 -> 522.32 | R5: =M5-Q5 -> 4700.88 | S5: =R5-N5 -> 825.53 | T5: =_xlfn.XLOOKUP(C5,Customers!A:A,Customers!D:D) -> M | U5: =_xlfn.XLOOKUP(C5,Customers!A:A,Customers!E:E) -> 38540 | V5: =_xlfn.XLOOKUP(C5,Customers!A:A,Customers!F:F) -> South Jennifer | W5: =_xlfn.XLOOKUP(C5,Customers!A:A,Customers!G:G) -> 45897 | X5: =DATEDIF(U5, TODAY(),"Y") -> 20 | Y5: =IF(X5<=25,"18-25",IF(X5<=35,"26-35", IF(X5<=50,"36-50","50+"))) -> 18-25
A6: T00005 | B6: 45533 | C6: C141 | D6: P036 | E6: S001 | F6: 3 | G6: 0.1 | H6: Credit Card | I6: =_xlfn.XLOOKUP(D6,Products!A:A,Products!E:E) -> 1501.46 | J6: =_xlfn.XLOOKUP(D6,Products!A:A,Products!F:F) -> 1167.73 | K6: =_xlfn.XLOOKUP(D6,Products!A:A,Products!C:C) -> Fashion | L6: =_xlfn.XLOOKUP(D6,Products!A:A,Products!D:D) -> Watches | M6: =F6*I6 -> 4504.38 | N6: =F6*J6 -> 3503.19 | O6: =M6-N6 -> 1001.19 | P6: =O6/M6 -> 0.22227032 | Q6: =M6*G6 -> 450.438 | R6: =M6-Q6 -> 4053.942 | S6: =R6-N6 -> 550.752 | T6: =_xlfn.XLOOKUP(C6,Customers!A:A,Customers!D:D) -> F | U6: =_xlfn.XLOOKUP(C6,Customers!A:A,Customers!E:E) -> 28708 | V6: =_xlfn.XLOOKUP(C6,Customers!A:A,Customers!F:F) -> Allisonmouth | W6: =_xlfn.XLOOKUP(C6,Customers!A:A,Customers!G:G) -> 45298 | X6: =DATEDIF(U6, TODAY(),"Y") -> 47 | Y6: =IF(X6<=25,"18-25",IF(X6<=35,"26-35", IF(X6<=50,"36-50","50+"))) -> 36-50
A7: T00006 | B7: 45744 | C7: C111 | D7: P036 | E7: S005 | F7: 5 | G7: 0.1 | H7: Mobile Money | I7: =_xlfn.XLOOKUP(D7,Products!A:A,Products!E:E) -> 1501.46 | J7: =_xlfn.XLOOKUP(D7,Products!A:A,Products!F:F) -> 1167.73 | K7: =_xlfn.XLOOKUP(D7,Products!A:A,Products!C:C) -> Fashion | L7: =_xlfn.XLOOKUP(D7,Products!A:A,Products!D:D) -> Watches | M7: =F7*I7 -> 7507.3 | N7: =F7*J7 -> 5838.65 | O7: =M7-N7 -> 1668.65 | P7: =O7/M7 -> 0.22227032 | Q7: =M7*G7 -> 750.73 | R7: =M7-Q7 -> 6756.57 | S7: =R7-N7 -> 917.92 | T7: =_xlfn.XLOOKUP(C7,Customers!A:A,Customers!D:D) -> M | U7: =_xlfn.XLOOKUP(C7,Customers!A:A,Customers!E:E) -> 34163 | V7: =_xlfn.XLOOKUP(C7,Customers!A:A,Customers!F:F) -> Justintown | W7: =_xlfn.XLOOKUP(C7,Customers!A:A,Customers!G:G) -> 44573 | X7: =DATEDIF(U7, TODAY(),"Y") -> 32 | Y7: =IF(X7<=25,"18-25",IF(X7<=35,"26-35", IF(X7<=50,"36-50","50+"))) -> 26-35
A8: T00007 | B8: 45605 | C8: C114 | D8: P009 | E8: S004 | F8: 2 | G8: 0.15 | H8: Credit Card | I8: =_xlfn.XLOOKUP(D8,Products!A:A,Products!E:E) -> 123.19 | J8: =_xlfn.XLOOKUP(D8,Products!A:A,Products!F:F) -> 80.36 | K8: =_xlfn.XLOOKUP(D8,Products!A:A,Products!C:C) -> Groceries | L8: =_xlfn.XLOOKUP(D8,Products!A:A,Products!D:D) -> Snacks | M8: =F8*I8 -> 246.38 | N8: =F8*J8 -> 160.72 | O8: =M8-N8 -> 85.66 | P8: =O8/M8 -> 0.34767432 | Q8: =M8*G8 -> 36.957 | R8: =M8-Q8 -> 209.423 | S8: =R8-N8 -> 48.703 | T8: =_xlfn.XLOOKUP(C8,Customers!A:A,Customers!D:D) -> F | U8: =_xlfn.XLOOKUP(C8,Customers!A:A,Customers!E:E) -> 29406 | V8: =_xlfn.XLOOKUP(C8,Customers!A:A,Customers!F:F) -> Adkinsport | W8: =_xlfn.XLOOKUP(C8,Customers!A:A,Customers!G:G) -> 45892 | X8: =DATEDIF(U8, TODAY(),"Y") -> 45 | Y8: =IF(X8<=25,"18-25",IF(X8<=35,"26-35", IF(X8<=50,"36-50","50+"))) -> 36-50
A9: T00008 | B9: 45440 | C9: C169 | D9: P005 | E9: S001 | F9: 3 | G9: 0.1 | H9: Cash | I9: =_xlfn.XLOOKUP(D9,Products!A:A,Products!E:E) -> 1396.22 | J9: =_xlfn.XLOOKUP(D9,Products!A:A,Products!F:F) -> 1004.09 | K9: =_xlfn.XLOOKUP(D9,Products!A:A,Products!C:C) -> Fashion | L9: =_xlfn.XLOOKUP(D9,Products!A:A,Products!D:D) -> Bags | M9: =F9*I9 -> 4188.66 | N9: =F9*J9 -> 3012.27 | O9: =M9-N9 -> 1176.39 | P9: =O9/M9 -> 0.28085116 | Q9: =M9*G9 -> 418.866 | R9: =M9-Q9 -> 3769.794 | S9: =R9-N9 -> 757.524 | T9: =_xlfn.XLOOKUP(C9,Customers!A:A,Customers!D:D) -> M | U9: =_xlfn.XLOOKUP(C9,Customers!A:A,Customers!E:E) -> 24638 | V9: =_xlfn.XLOOKUP(C9,Customers!A:A,Customers!F:F) -> Christopherburgh | W9: =_xlfn.XLOOKUP(C9,Customers!A:A,Customers!G:G) -> 44553 | X9: =DATEDIF(U9, TODAY(),"Y") -> 59 | Y9: =IF(X9<=25,"18-25",IF(X9<=35,"26-35", IF(X9<=50,"36-50","50+"))) -> 50+
A10: T00009 | B10: 45539 | C10: C193 | D10: P035 | E10: S002 | F10: 3 | G10: 0.05 | H10: Credit Card | I10: =_xlfn.XLOOKUP(D10,Products!A:A,Products!E:E) -> 1562.43 | J10: =_xlfn.XLOOKUP(D10,Products!A:A,Products!F:F) -> 1195.63 | K10: =_xlfn.XLOOKUP(D10,Products!A:A,Products!C:C) -> Electronics | L10: =_xlfn.XLOOKUP(D10,Products!A:A,Products!D:D) -> Laptop | M10: =F10*I10 -> 4687.29 | N10: =F10*J10 -> 3586.89 | O10: =M10-N10 -> 1100.4 | P10: =O10/M10 -> 0.23476252 | Q10: =M10*G10 -> 234.3645 | R10: =M10-Q10 -> 4452.9255 | S10: =R10-N10 -> 866.0355 | T10: =_xlfn.XLOOKUP(C10,Customers!A:A,Customers!D:D) -> F | U10: =_xlfn.XLOOKUP(C10,Customers!A:A,Customers!E:E) -> 25513 | V10: =_xlfn.XLOOKUP(C10,Customers!A:A,Customers!F:F) -> North Kelly | W10: =_xlfn.XLOOKUP(C10,Customers!A:A,Customers!G:G) -> 44173 | X10: =DATEDIF(U10, TODAY(),"Y") -> 56 | Y10: =IF(X10<=25,"18-25",IF(X10<=35,"26-35", IF(X10<=50,"36-50","50+"))) -> 50+
A11: T00010 | B11: 45459 | C11: C038 | D11: P045 | E11: S001 | F11: 1 | G11: 0.05 | H11: Mobile Money | I11: =_xlfn.XLOOKUP(D11,Products!A:A,Products!E:E) -> 1879.08 | J11: =_xlfn.XLOOKUP(D11,Products!A:A,Products!F:F) -> 1004.56 | K11: =_xlfn.XLOOKUP(D11,Products!A:A,Products!C:C) -> Groceries | L11: =_xlfn.XLOOKUP(D11,Products!A:A,Products!D:D) -> Dairy | M11: =F11*I11 -> 1879.08 | N11: =F11*J11 -> 1004.56 | O11: =M11-N11 -> 874.52 | P11: =O11/M11 -> 0.46539796 | Q11: =M11*G11 -> 93.954 | R11: =M11-Q11 -> 1785.126 | S11: =R11-N11 -> 780.566 | T11: =_xlfn.XLOOKUP(C11,Customers!A:A,Customers!D:D) -> M | U11: =_xlfn.XLOOKUP(C11,Customers!A:A,Customers!E:E) -> 27138 | V11: =_xlfn.XLOOKUP(C11,Customers!A:A,Customers!F:F) -> Wilsonbury | W11: =_xlfn.XLOOKUP(C11,Customers!A:A,Customers!G:G) -> 44326 | X11: =DATEDIF(U11, TODAY(),"Y") -> 52 | Y11: =IF(X11<=25,"18-25",IF(X11<=35,"26-35", IF(X11<=50,"36-50","50+"))) -> 50+
A12: T00011 | B12: 45725 | C12: C157 | D12: P022 | E12: S001 | F12: 4 | G12: 0.15 | H12: Credit Card | I12: =_xlfn.XLOOKUP(D12,Products!A:A,Products!E:E) -> 25.57 | J12: =_xlfn.XLOOKUP(D12,Products!A:A,Products!F:F) -> 19.05 | K12: =_xlfn.XLOOKUP(D12,Products!A:A,Products!C:C) -> Groceries | L12: =_xlfn.XLOOKUP(D12,Products!A:A,Products!D:D) -> Vegetables | M12: =F12*I12 -> 102.28 | N12: =F12*J12 -> 76.2 | O12: =M12-N12 -> 26.08 | P12: =O12/M12 -> 0.25498631 | Q12: =M12*G12 -> 15.342 | R12: =M12-Q12 -> 86.938 | S12: =R12-N12 -> 10.738 | T12: =_xlfn.XLOOKUP(C12,Customers!A:A,Customers!D:D) -> M | U12: =_xlfn.XLOOKUP(C12,Customers!A:A,Customers!E:E) -> 24092 | V12: =_xlfn.XLOOKUP(C12,Customers!A:A,Customers!F:F) -> Port Patriciaburgh | W12: =_xlfn.XLOOKUP(C12,Customers!A:A,Customers!G:G) -> 44917 | X12: =DATEDIF(U12, TODAY(),"Y") -> 60 | Y12: =IF(X12<=25,"18-25",IF(X12<=35,"26-35", IF(X12<=50,"36-50","50+"))) -> 50+
A13: T00012 | B13: 45449 | C13: C184 | D13: P042 | E13: S004 | F13: 4 | G13: 0.15 | H13: Credit Card | I13: =_xlfn.XLOOKUP(D13,Products!A:A,Products!E:E) -> 453.62 | J13: =_xlfn.XLOOKUP(D13,Products!A:A,Products!F:F) -> 316.63 | K13: =_xlfn.XLOOKUP(D13,Products!A:A,Products!C:C) -> Fashion | L13: =_xlfn.XLOOKUP(D13,Products!A:A,Products!D:D) -> Clothing | M13: =F13*I13 -> 1814.48 | N13: =F13*J13 -> 1266.52 | O13: =M13-N13 -> 547.96 | P13: =O13/M13 -> 0.30199286 | Q13: =M13*G13 -> 272.172 | R13: =M13-Q13 -> 1542.308 | S13: =R13-N13 -> 275.788 | T13: =_xlfn.XLOOKUP(C13,Customers!A:A,Customers!D:D) -> M | U13: =_xlfn.XLOOKUP(C13,Customers!A:A,Customers!E:E) -> 37724 | V13: =_xlfn.XLOOKUP(C13,Customers!A:A,Customers!F:F) -> West Katrina | W13: =_xlfn.XLOOKUP(C13,Customers!A:A,Customers!G:G) -> 44305 | X13: =DATEDIF(U13, TODAY(),"Y") -> 23 | Y13: =IF(X13<=25,"18-25",IF(X13<=35,"26-35", IF(X13<=50,"36-50","50+"))) -> 18-25
... A5001: T05000 | B5001: 45489 | C5001: C053 | D5001: P034 | E5001: S004 | F5001: 5 | G5001: 0.15 | H5001: Cash | I5001: =_xlfn.XLOOKUP(D5001,Products!A:A,Products!E:E) -> 428.05 | J5001: =_xlfn.XLOOKUP(D5001,Products!A:A,Products!F:F) -> 246.07 | K5001: =_xlfn.XLOOKUP(D5001,Products!A:A,Products!C:C) -> Electronics | L5001: =_xlfn.XLOOKUP(D5001,Products!A:A,Products!D:D) -> Laptop | M5001: =F5001*I5001 -> 2140.25 | N5001: =F5001*J5001 -> 1230.35 | O5001: =M5001-N5001 -> 909.9 | P5001: =O5001/M5001 -> 0.42513725 | Q5001: =M5001*G5001 -> 321.0375 | R5001: =M5001-Q5001 -> 1819.2125 | S5001: =R5001-N5001 -> 588.8625 | T5001: =_xlfn.XLOOKUP(C5001,Customers!A:A,Customers!D:D) -> F | U5001: =_xlfn.XLOOKUP(C5001,Customers!A:A,Customers!E:E) -> 35905 | V5001: =_xlfn.XLOOKUP(C5001,Customers!A:A,Customers!F:F) -> Lake Michaelshire | W5001: =_xlfn.XLOOKUP(C5001,Customers!A:A,Customers!G:G) -> 45389 | X5001: =DATEDIF(U5001, TODAY(),"Y") -> 28 | Y5001: =IF(X5001<=25,"18-25",IF(X5001<=35,"26-35", IF(X5001<=50,"36-50","50+"))) -> 26-35

Sheet Age Analysis
A3: Age Analysis | B3: Sum of Revenue | C3: Sum of Net Profit | D3: Count of TransactionID
A4: 18-25 | B4: 2281544.5 | C4: 554110.13 | D4: 727
A5: 26-35 | B5: 2581873.4 | C5: 649405.92 | D5: 840
A6: 36-50 | B6: 4439428.4 | C6: 1100904.2 | D6: 1428
A7: 50+ | B7: 6172325.4 | C7: 1521894.4 | D7: 2005
A8: Grand Total | B8: 15475172 | C8: 3826314.7 | D8: 5000

Sheet customer count
A3: Row Labels | B3: Count of CustomerID
A4: F | B4: 2190
A5: M | B5: 2810
A6: Grand Total | B6: 5000

Sheet Store Performance Analysis
A3: Row Labels | B3: Sum of Revenue | C3: Sum of Net Profit | D3: Count of TransactionID
A4: S003 | B4: 3156086.8 | C4: 804011.47 | D4: 1013
A5: S005 | B5: 3073853.5 | C5: 772924.95 | D5: 953
A6: S004 | B6: 3143257.8 | C6: 769983.35 | D6: 1011
A7: S001 | B7: 3121777 | C7: 753860.93 | D7: 1014
A8: S002 | B8: 2980196.5 | C8: 725533.97 | D8: 1009
A9: Grand Total | B9: 15475172 | C9: 3826314.7 | D9: 5000

Sheet Monthly Trend
A3: Row Labels | B3: Sum of Revenue
A4: 2023 | B4: 2359985.1
A5: Sep | B5: 411958.8
A6: Oct | B6: 605212.81
A7: Nov | B7: 637527.83
A8: Dec | B8: 705285.68
A9: 2024 | B9: 7598137.3
A10: Jan | B10: 630548.83
A11: Feb | B11: 583639.5
A12: Mar | B12: 599539.34
A13: Apr | B13: 640993.92
A14: May | B14: 613932.08
A15: Jun | B15: 682260.45
... A32: Grand Total | B32: 15475172

Sheet Category Analysis
A3: Row Labels | B3: Sum of Revenue | C3: Sum of Net Profit
A4: Electronics | B4: 6836766.1 | C4: 1632229
A5: Fashion | B5: 6740381.4 | C5: 1660525.2
A6: Groceries | B6: 1898024.2 | C6: 533560.53
A7: Grand Total | B7: 15475172 | C7: 3826314.7

Sheet Dashboard_KPI'S
A1: KPI
A2: Total Revenue | B2: =SUM(Sales_Master!M:M) -> 15475172
A3: Total Net Revenue | B3: =SUM(Sales_Master!R:R) -> 14301903
A4: Total Profit | B4: =SUM(Sales_Master!S:S) -> 3826314.7
A5: Total Orders | B5: =COUNTA(Sales_Master!A2:A5001) -> 5000
A6: Total Quantity Sold | B6: =SUM(Sales_Master!F:F) -> 14949
A7: Average Order Value | B7: =B2/B5 -> 3095.0343
